Workbook

Sheet WORKSHEET
A2: 54 Emekuku Street , D-Line
A3: Port Harcourt Rivers State , Nigeria
A4: Tel: +234(84)360759
A5: Fax: (713) 640-7478
A6: Email: sales@plantengrg.com
A7: URL: www.plantengrg.com
A9: =TODAY() -> 42361
A10: Customer
U11: OUR RFQ#: PEHG638
A12: Customer RFQ#
A13: ITEM NO | B13: DESCRIPTION | C13: QTY | D13: Unit Cost | F13: Discount | G13: FOB EX WORKS | H13: EXPORT PACKAGING (% OF FOB) | I13: INSURANCE (1% OF FOB) | J13: FREIGHT | K13: CIF Foreign Cost :A | L13: HS TARRIFF | M13: Pre Shipment Inspections ( 1% of FOB ) Statutory | N13: Custom Duty ( % Applicable HS code ) Statutory | O13: Custom Surcharge ( 7% of custom duty ) - Statutory) | P13: ETLS Charge ( 0.5% of CIF ) Statutory | Q13: Loal Handling ( 5% of CIF ) | R13: custom vat | S13: Local Mark - Up ( % of CIF ) | T13: Local Cost B | U13: DDP PRICE A + B = C | V13: BILL TO TOTAL
H14: 0 | I14: 0 | J14: 0 | M14: 0 | O14: 0 | P14: 0 | Q14: 0.05 | R14: 0 | S14: 0.15 | V14: F + G
A15: 1 | B15: 1619575 CHEMICAL, ZOK 27 DETERGENT 209L DRUM FOR TURBINE CLEANING MFR: ZOKMAN PRODUCTS Manufacturer Part No : ZOK 27 Manufacturer : ZOKMAN PRODUCTS INC. | C15: 4 | D15: 1440 | E15: =D15 -> 1440 | F15: =D15*$F$14 -> 0 | G15: =D15-F15 -> 1440 | H15: =G15*$H$14 -> 0 | I15: =G15*$I$14 -> 0 | J15: =G15*$J$14 -> 0 | K15: =SUM(G15:J15) -> 1440 | L15: 0 | M15: =G15*$M$14 -> 0 | N15: =L15*K15 -> 0 | O15: =N15*$O$14 -> 0 | P15: =K15*$P$14 -> 0 | Q15: =K15*$Q$14 -> 72 | R15: =R14*(K15+M15+N15+O15+$P15) -> 0 | S15: =G15*$S$14 -> 216 | T15: =SUM(M15:S15) -> 288 | U15: =K15+T15 -> 1728 | V15: =U15 -> 1728
B16: 1626404 FLUID, WASH, 25 LITRES TYPE: ZOK 27 MFR: ZOKMAN PRODUCTS INC. U.S.A Manufacturer Part No : ZOK 27 Manufacturer : ZOKMAN PRODUCTS INC. | C16: 11 | D16: 262 | E16: =D16 -> 262 | F16: =D16*$F$14 -> 0 | G16: =D16-F16 -> 262 | H16: =G16*$H$14 -> 0 | I16: =G16*$I$14 -> 0 | J16: =G16*$J$14 -> 0 | K16: =SUM(G16:J16) -> 262 | L16: 0 | M16: =G16*$M$14 -> 0 | N16: =L16*K16 -> 0 | O16: =N16*$O$14 -> 0 | P16: =K16*$P$14 -> 0 | Q16: =K16*$Q$14 -> 13.1 | R16: =R15*(K16+M16+N16+O16+$P16) -> 0 | S16: =G16*$S$14 -> 39.3 | T16: =SUM(M16:S16) -> 52.4 | U16: =K16+T16 -> 314.4 | V16: =U16 -> 314.4
B17: 1618231 OIL, PENETRATING, WD-40 200 ML AEROSOL Manufacturer Part No : NO PART NUMBER Manufacturer : NO SPECIFIC MANUFACTURER | C17: 31 | E17: =D17 -> 0 | F17: =D17*$F$14 -> 0 | G17: =D17-F17 -> 0 | H17: =G17*$H$14 -> 0 | I17: =G17*$I$14 -> 0 | J17: =G17*$J$14 -> 0 | K17: =SUM(G17:J17) -> 0 | L17: 0 | M17: =G17*$M$14 -> 0 | N17: =L17*K17 -> 0 | O17: =N17*$O$14 -> 0 | P17: =K17*$P$14 -> 0 | Q17: =K17*$Q$14 -> 0 | R17: =R16*(K17+M17+N17+O17+$P17) -> 0 | S17: =G17*$S$14 -> 0 | T17: =SUM(M17:S17) -> 0 | U17: =K17+T17 -> 0 | V17: =U17 -> 0
A18: 2 | B18: 2642271 OIL PENETRATING WD-40 400ML AEROSOL Manufacturer Part No : NO PART NUMBER Manufacturer : NO SPECIFIC MANUFACTURER | C18: 50 | D18: 5.33 | E18: =D18 -> 5.33 | F18: =D18*$F$14 -> 0 | G18: =D18-F18 -> 5.33 | H18: =G18*$H$14 -> 0 | I18: =G18*$I$14 -> 0 | J18: =G18*$J$14 -> 0 | K18: =SUM(G18:J18) -> 5.33 | L18: 0 | M18: =G18*$M$14 -> 0 | N18: =L18*K18 -> 0 | O18: =N18*$O$14 -> 0 | P18: =K18*$P$14 -> 0 | Q18: =K18*$Q$14 -> 0.2665 | R18: =R17*(K18+M18+N18+O18+$P18) -> 0 | S18: =G18*$S$14 -> 0.7995 | T18: =SUM(M18:S18) -> 1.066 | U18: =K18+T18 -> 6.396 | V18: =U18 -> 6.396
A19: 3 | B19: 1619516 CHEMICAL, DISPERSANT DISPOLENE 36S 209 LITRE DRUM MFR: SEPPIC Manufacturer Part No : 36S Manufacturer : NO SPECIFIC MANUFACTURER | C19: 4 | D19: 640.56 | E19: =D19 -> 640.56 | F19: =D19*$F$14 -> 0 | G19: =D19-F19 -> 640.56 | H19: =G19*$H$14 -> 0 | I19: =G19*$I$14 -> 0 | J19: =G19*$J$14 -> 0 | K19: =SUM(G19:J19) -> 640.56 | L19: 0 | M19: =G19*$M$14 -> 0 | N19: =L19*K19 -> 0 | O19: =N19*$O$14 -> 0 | P19: =K19*$P$14 -> 0 | Q19: =K19*$Q$14 -> 32.028 | R19: =R18*(K19+M19+N19+O19+$P19) -> 0 | S19: =G19*$S$14 -> 96.084 | T19: =SUM(M19:S19) -> 128.112 | U19: =K19+T19 -> 768.672 | V19: =U19 -> 768.672

Sheet SUBMISSION SHEET
A11: TO:
A12: CUSTOMER | D12: TOTAL E&P NIGERIA LIMITED
A13: CONTACT NAME | D13: PRIVILEGE ADAGBONYIN
A14: CUSTOMER REF | D14: 6060059393
F15: DATE: | H15: 21ST OF DEC, 2015
F16: QUOTATION REF NUMBER: | H16: PEDM1124
A18: ITEM NO. | B18: QTY | C18: UOM | D18: DESCRIPTION | E18: UNIT PRICE | F18: EXT. PRICE | G18: DELIVERY LEADTIME | H18: DELIVERY LOCATION
A19: 1 | B19: 4 | C19: DRUMS | D19: 1619575 CHEMICAL, ZOK 27 DETERGENT 209L DRUM FOR TURBINE CLEANING MFR: ZOKMAN PRODUCTS Manufacturer Part No : ZOK 27 Manufacturer : ZOKMAN PRODUCTS INC. | E19: =WORKSHEET!U15 -> 1728 | F19: =E19*B19 -> 6912 | G19: 3 WEEKS | H19: TOTAL ONNE BASE
A20: 2 | B20: 11 | C20: EA | D20: 1626404 FLUID, WASH, 25 LITRES TYPE: ZOK 27 MFR: ZOKMAN PRODUCTS INC. U.S.A Manufacturer Part No : ZOK 27 Manufacturer : ZOKMAN PRODUCTS INC. | E20: =WORKSHEET!U16 -> 314.4 | F20: =E20*B20 -> 3458.4 | G20: 3 WEEKS | H20: TOTAL ONNE BASE
A21: 3 | B21: 31 | C21: EA | D21: 1618231 OIL, PENETRATING, WD-40 200 ML AEROSOL Manufacturer Part No : NO PART NUMBER Manufacturer : NO SPECIFIC MANUFACTURER PLEASE NOTE: ITEM IS NOT AVALIABLE, AWAITING QUOTE FROM THE MANUFACTURER. | E21: =WORKSHEET!U17 -> 0 | F21: =E21*B21 -> 0
A22: 4 | B22: 50 | C22: EA | D22: 2642271 OIL PENETRATING WD-40 400ML AEROSOL Manufacturer Part No : NO PART NUMBER Manufacturer : NO SPECIFIC MANUFACTURER | E22: =WORKSHEET!U18 -> 6.396 | F22: =E22*B22 -> 319.8 | G22: 3 WEEKS | H22: TOTAL ONNE BASE
A23: 5 | B23: 4 | C23: DRUMS | D23: 1619516 CHEMICAL, DISPERSANT DISPOLENE 36S 209 LITRE DRUM MFR: SEPPIC Manufacturer Part No : 36S Manufacturer : NO SPECIFIC MANUFACTURER | E23: =WORKSHEET!U19 -> 768.672 | F23: =E23*B23 -> 3074.688 | G23: 3 WEEKS | H23: TOTAL ONNE BASE
A24: TOTAL DDP | F24: =SUM(F19:F23) -> 13764.888
A27: QUOTATION TERMS. Currency: All Prices Quoted are in USD Incoterms: The incoterms used in the offer is DDP Place of Delivery: TOTAL, ONNE BASE, Rivers State. Nigeria. Taxes: All Prices are EXCLUSIVE of all local taxes. Quote Validity: The validity of this offer is 30 days from the date of the quotation. Delivery Lead-time: 3 weeks after receipt of an official purchase Order. Quoted lead-times are based on current OEM stocking level and subject to change. Payment Terms: Customer's Payment Terms Partial order: Prices are based on complete order only, in case of a partial offer, a review will be done and a revised offer sent Minimum order Value: Our minimum order Value is USD 300 or it's equivalent.
A30: AUTHORISED SIGNATURE FOR PENL
A45: 1 OF 1

Sheet Sheet1 (2)
A18: 54 Emekuku Street , D-Line
A19: Port Harcourt Rivers State , Nigeria
A20: Tel: +234(84)360759
A21: Email: sales@plantengrg.com
A22: URL: www.plantengrg.com
G23: QUOTATION
A24: Date:27/02/2014 | H24: PENA186
A25: Customer: CHEVRON NIGERIA LTD
A26: Customer RFQ#: PR21284120
A28: ITEM NO. | B28: QTY | D28: DESCRIPTION | E28: UNIT PRICE | F28: EXT. PRICE | G28: DELIVERY | H28: EX-WORKS LOCATION
A29: 1 | B29: 5 | C29: EA | D29: CELL:SENSOR, OXYGEN,FLEXI-DIP,Oxy gen Sensor Cell,part # SNS-A2615-17, used with Flexi-Dip Oxygen Sensor Gauging Tape. Supplier: MMC International Corp. 60 Inip Drive, Inwood, New York 11096-0664Phone# 1-800-645-7339Fax- 1-516-371-3134. Man uf Part No : SNS-A2615-17. Ref : JDE Symbol # 97808508 | E29: =WORKSHEET!#REF! -> #REF! | F29: =E29*B29 -> #REF! | G29: 6 WEEKS | H29: USA
A30: TOTAL | F30: =SUM(F29:F29) -> #REF!
A31: VAT 5% | F31: =F30*0.05 -> #REF!
A32: TOTAL DDP | F32: =F30+F31 -> #REF!
A37: The price and/or discount in this quotation are based on a complete order only.
A39: AUTHORISED SIGNATURE FOR PLANT ENGINEERING
A54: 1 OF 1

Sheet Sheet2

Sheet Sheet3
